chilli/CairoNumberWidth.py
chilli/DegenerateSeqConvetor.py
chilli/FastaFormatParser.py
chilli/FastaIterator.py
chilli/FastaRemoveRedundant.py
chilli/FastaSimpleFormatParser.py
chilli/GelMobility.py
chilli/MFEprimerParser.py
chilli/PenultimateTable.py
chilli/Seq.py
chilli/SeqCheck.py
chilli/ThermodynamicsParameters.py
chilli/TmDeltaG.py
chilli/UniFastaFormat.py
chilli/__init__.py
chilli/chilli.py
chilli/conv_shelve_json.py
chilli/mfe_index_db.py
chilli/mve.py
chilli/ve.py
mfeprimer_py3-0.1.2.data/data/bin/MFEprimer_Darwin_32_faToTwoBit
mfeprimer_py3-0.1.2.data/data/bin/MFEprimer_Darwin_32_twoBitToFa
mfeprimer_py3-0.1.2.data/data/bin/MFEprimer_Darwin_64_faToTwoBit
mfeprimer_py3-0.1.2.data/data/bin/MFEprimer_Darwin_64_twoBitToFa
mfeprimer_py3-0.1.2.data/data/bin/MFEprimer_Linux_32_faToTwoBit
mfeprimer_py3-0.1.2.data/data/bin/MFEprimer_Linux_32_twoBitToFa
mfeprimer_py3-0.1.2.data/data/bin/MFEprimer_Linux_64_faToTwoBit
mfeprimer_py3-0.1.2.data/data/bin/MFEprimer_Linux_64_twoBitToFa
mfeprimer_py3-0.1.2.data/scripts/IndexDB.py
mfeprimer_py3-0.1.2.data/scripts/MFEprimer.py
mfeprimer_py3-0.1.2.data/scripts/UniFastaFormat.py
mfeprimer_py3-0.1.2.data/scripts/mfe_index_db.py
mfeprimer_py3-0.1.2.dist-info/METADATA
mfeprimer_py3-0.1.2.dist-info/WHEEL
mfeprimer_py3-0.1.2.dist-info/top_level.txt
mfeprimer_py3-0.1.2.dist-info/RECORD
