Metadata-Version: 2.1
Name: mfeprimer-py3
Version: 0.1.2
Summary: UNKNOWN
Home-page: https://github.com/Ulises-Rosas/mfeprimer-py3
License: UNKNOWN
Platform: UNKNOWN
Classifier: Programming Language :: Python :: 3
Requires-Dist: psutil
